lmax_sdk/__init__.py
lmax_sdk/account/__init__.py
lmax_sdk/account/account_data.py
lmax_sdk/account/trading.py
lmax_sdk/broker_market_data/__init__.py
lmax_sdk/broker_market_data/market_data.py
lmax_sdk/client.py
lmax_sdk/public_data/__init__.py
lmax_sdk/public_data/public.py
lmax_sdk/validation.py
lmax_sdk-1.0.0.dist-info/LICENSE
lmax_sdk-1.0.0.dist-info/METADATA
lmax_sdk-1.0.0.dist-info/WHEEL
lmax_sdk-1.0.0.dist-info/RECORD
