Metadata-Version: 2.1
Name: lmax-sdk
Version: 1.0.0
Summary: Python SDK for LMAX Global
Home-page: https://github.com/adradr/lmax-sdk
License: MIT
Author: Adrian Lenard
Author-email: adrian.lenard@me.com
Classifier: License :: OSI Approved :: MIT License
Classifier: Programming Language :: Python :: 2
Classifier: Programming Language :: Python :: 2.7
Classifier: Programming Language :: Python :: 3
Classifier: Programming Language :: Python :: 3.4
Classifier: Programming Language :: Python :: 3.5
Classifier: Programming Language :: Python :: 3.6
Classifier: Programming Language :: Python :: 3.7
Classifier: Programming Language :: Python :: 3.8
Classifier: Programming Language :: Python :: 3.9
Classifier: Programming Language :: Python :: 3.10
Classifier: Programming Language :: Python :: 3.11
Classifier: Programming Language :: Python :: 3.12
Requires-Dist: pdoc
Requires-Dist: requests
Project-URL: Homepage, https://github.com/adradr/lmax-python-sdk.git
